azure/kusto/data/__init__.py
azure/kusto/data/_cloud_settings.py
azure/kusto/data/_converters.py
azure/kusto/data/_decorators.py
azure/kusto/data/_models.py
azure/kusto/data/_string_utils.py
azure/kusto/data/_telemetry.py
azure/kusto/data/_token_providers.py
azure/kusto/data/_version.py
azure/kusto/data/aio/__init__.py
azure/kusto/data/aio/_models.py
azure/kusto/data/aio/client.py
azure/kusto/data/aio/response.py
azure/kusto/data/aio/streaming_response.py
azure/kusto/data/client.py
azure/kusto/data/client_base.py
azure/kusto/data/client_details.py
azure/kusto/data/client_request_properties.py
azure/kusto/data/data_format.py
azure/kusto/data/env_utils.py
azure/kusto/data/exceptions.py
azure/kusto/data/helpers.py
azure/kusto/data/kcsb.json
azure/kusto/data/kcsb.py
azure/kusto/data/kusto_trusted_endpoints.py
azure/kusto/data/py.typed
azure/kusto/data/response.py
azure/kusto/data/security.py
azure/kusto/data/streaming_response.py
azure/kusto/data/wellKnownKustoEndpoints.json
azure_kusto_data-6.0.1.dist-info/WHEEL
azure_kusto_data-6.0.1.dist-info/METADATA
azure_kusto_data-6.0.1.dist-info/RECORD
