Metadata-Version: 2.4
Name: azure-kusto-data
Version: 6.0.1
Summary: Kusto Data Client
Keywords: azure,kusto,data,analytics
Author: Microsoft Corporation
Author-email: Microsoft Corporation <kustalk@microsoft.com>
License-Expression: MIT
Classifier: Programming Language :: Python
Classifier: Programming Language :: Python :: 3.9
Classifier: Programming Language :: Python :: 3.10
Classifier: Programming Language :: Python :: 3.11
Classifier: Programming Language :: Python :: 3.12
Classifier: Programming Language :: Python :: 3.13
Classifier: License :: OSI Approved :: MIT License
Requires-Dist: python-dateutil>=2.9.0
Requires-Dist: requests>=2.32.4
Requires-Dist: azure-identity>=1.24.0,<2
Requires-Dist: msal>=1.34.0b1,<2
Requires-Dist: ijson~=3.4.0
Requires-Dist: azure-core>=1.35.0,<2
Requires-Dist: aiohttp>=3.12.15 ; extra == 'aio'
Requires-Dist: asgiref>=3.9.1 ; extra == 'aio'
Requires-Dist: pandas>=2.3.1 ; extra == 'pandas'
Requires-Python: >=3.9
Project-URL: Repository, https://github.com/Azure/azure-kusto-python
Provides-Extra: aio
Provides-Extra: pandas
